pptx_renderer/__init__.py
pptx_renderer/command_line.py
pptx_renderer/exceptions.py
pptx_renderer/plugins.py
pptx_renderer/pptx_renderer.py
pptx_renderer/utils.py
pptx_renderer-0.5.2.dist-info/LICENSE
pptx_renderer-0.5.2.dist-info/METADATA
pptx_renderer-0.5.2.dist-info/WHEEL
pptx_renderer-0.5.2.dist-info/entry_points.txt
pptx_renderer-0.5.2.dist-info/top_level.txt
pptx_renderer-0.5.2.dist-info/RECORD
