Metadata-Version: 2.1
Name: pptx_renderer
Version: 0.5.2
Summary: Render ppt like a jupyter notebook
Author-email: Najeem Muhammed <najeem@gmail.com>
License: MIT License
Project-URL: Homepage, https://github.com/idling-mind/pptx_renderer
Project-URL: Bug Tracker, https://github.com/idling-mind/pptx_renderer/issues
Keywords: powerpoint,ppt,pptx,presentation,slides
Classifier: Programming Language :: Python :: 3
Classifier: License :: OSI Approved :: MIT License
Classifier: Operating System :: OS Independent
Requires-Python: >=3.7
License-File: LICENSE
Requires-Dist: python-pptx
Requires-Dist: click
Requires-Dist: Pillow>=9.3
Provides-Extra: test
Requires-Dist: pytest; extra == "test"
Requires-Dist: coverage; extra == "test"
